CHANGES.txt
MANIFEST.in
README.txt
setup.cfg
setup.py
src/cloudooo/__init__.py
src/cloudooo.handler.ooo.egg-info/PKG-INFO
src/cloudooo.handler.ooo.egg-info/SOURCES.txt
src/cloudooo.handler.ooo.egg-info/dependency_links.txt
src/cloudooo.handler.ooo.egg-info/entry_points.txt
src/cloudooo.handler.ooo.egg-info/namespace_packages.txt
src/cloudooo.handler.ooo.egg-info/requires.txt
src/cloudooo.handler.ooo.egg-info/top_level.txt
src/cloudooo/handler/__init__.py
src/cloudooo/handler/ooo/__init__.py
src/cloudooo/handler/ooo/document.py
src/cloudooo/handler/ooo/filter.py
src/cloudooo/handler/ooo/granulator.py
src/cloudooo/handler/ooo/handler.py
src/cloudooo/handler/ooo/mimemapper.py
src/cloudooo/handler/ooo/application/__init__.py
src/cloudooo/handler/ooo/application/application.py
src/cloudooo/handler/ooo/application/openoffice.py
src/cloudooo/handler/ooo/helper/__init__.py
src/cloudooo/handler/ooo/helper/helper_utils.py
src/cloudooo/handler/ooo/helper/openoffice_tester.py
src/cloudooo/handler/ooo/helper/unoconverter.py
src/cloudooo/handler/ooo/helper/unomimemapper.py
src/cloudooo/handler/ooo/monitor/__init__.py
src/cloudooo/handler/ooo/monitor/memory.py
src/cloudooo/handler/ooo/monitor/monitor.py
src/cloudooo/handler/ooo/monitor/request.py
src/cloudooo/handler/ooo/monitor/sleeping_time.py
src/cloudooo/handler/ooo/monitor/timeout.py
src/cloudooo/handler/ooo/tests/HighTestLoad.py
src/cloudooo/handler/ooo/tests/HighTestLoadGranulate.py
src/cloudooo/handler/ooo/tests/__init__.py
src/cloudooo/handler/ooo/tests/runOOoHandlerUnitTest.py
src/cloudooo/handler/ooo/tests/testAllSupportedFormat.py
src/cloudooo/handler/ooo/tests/testAllSupportedFormatERP5Compatibility.py
src/cloudooo/handler/ooo/tests/testApplication.py
src/cloudooo/handler/ooo/tests/testFileSystemDocument.py
src/cloudooo/handler/ooo/tests/testFilter.py
src/cloudooo/handler/ooo/tests/testHighLoad.py
src/cloudooo/handler/ooo/tests/testInterface.py
src/cloudooo/handler/ooo/tests/testLegacyInterface.py
src/cloudooo/handler/ooo/tests/testMimemapper.py
src/cloudooo/handler/ooo/tests/testMonitorInit.py
src/cloudooo/handler/ooo/tests/testMonitorMemory.py
src/cloudooo/handler/ooo/tests/testMonitorRequest.py
src/cloudooo/handler/ooo/tests/testMonitorTimeout.py
src/cloudooo/handler/ooo/tests/testOOGranulator.py
src/cloudooo/handler/ooo/tests/testOOHandler.py
