Metadata-Version: 1.0
Name: cloudooo.handler.ooo
Version: 0.2
Summary: Python Package to handler OpenOffice.org Documents
Home-page: UNKNOWN
Author: Gabriel M. Monnerat
Author-email: gabriel@tiolive.com
License: GPLv3
Keywords: Python OpenOffice.org
Platform: UNKNOWN
Classifier: Programming Language :: Python :: 2.6
Classifier: Natural Language :: English
Classifier: Topic :: Software Development :: Libraries :: Python Modules
Classifier: License :: OSI Approved :: GNU General Public License (GPL)
